main.py
text_search.py
auto_find_date_pdf-0.2.22.dist-info/LICENSE
auto_find_date_pdf-0.2.22.dist-info/METADATA
auto_find_date_pdf-0.2.22.dist-info/WHEEL
auto_find_date_pdf-0.2.22.dist-info/entry_points.txt
auto_find_date_pdf-0.2.22.dist-info/top_level.txt
auto_find_date_pdf-0.2.22.dist-info/RECORD
