Metadata-Version: 2.1
Name: auto-find-date-pdf
Version: 0.2.22
Summary: A simple lib to find dates from any txt/ pdf/ docx/ rtf source. For documentation see
Author: Your Name
Author-email: open@marvsai.com
License-File: LICENSE
Requires-Dist: python-docx
Requires-Dist: pypdf
Requires-Dist: pytz
Requires-Dist: striprtf
Requires-Dist: Pillow
